<?xml version="1.0" encoding="UTF-8"?>
<dolfin xmlns:dolfin="http://fenicsproject.org">
  <mesh_function type="uint" dim="1" size="364">
    <entity index="0" value="0"/>
    <entity index="1" value="0"/>
    <entity index="2" value="0"/>
    <entity index="3" value="0"/>
    <entity index="4" value="0"/>
    <entity index="5" value="0"/>
    <entity index="6" value="0"/>
    <entity index="7" value="0"/>
    <entity index="8" value="0"/>
    <entity index="9" value="0"/>
    <entity index="10" value="0"/>
    <entity index="11" value="0"/>
    <entity index="12" value="0"/>
    <entity index="13" value="0"/>
    <entity index="14" value="0"/>
    <entity index="15" value="0"/>
    <entity index="16" value="0"/>
    <entity index="17" value="0"/>
    <entity index="18" value="0"/>
    <entity index="19" value="0"/>
    <entity index="20" value="0"/>
    <entity index="21" value="0"/>
    <entity index="22" value="0"/>
    <entity index="23" value="0"/>
    <entity index="24" value="0"/>
    <entity index="25" value="0"/>
    <entity index="26" value="0"/>
    <entity index="27" value="0"/>
    <entity index="28" value="0"/>
    <entity index="29" value="0"/>
    <entity index="30" value="0"/>
    <entity index="31" value="0"/>
    <entity index="32" value="0"/>
    <entity index="33" value="0"/>
    <entity index="34" value="0"/>
    <entity index="35" value="0"/>
    <entity index="36" value="0"/>
    <entity index="37" value="0"/>
    <entity index="38" value="0"/>
    <entity index="39" value="0"/>
    <entity index="40" value="0"/>
    <entity index="41" value="0"/>
    <entity index="42" value="0"/>
    <entity index="43" value="0"/>
    <entity index="44" value="0"/>
    <entity index="45" value="0"/>
    <entity index="46" value="0"/>
    <entity index="47" value="0"/>
    <entity index="48" value="0"/>
    <entity index="49" value="0"/>
    <entity index="50" value="0"/>
    <entity index="51" value="0"/>
    <entity index="52" value="0"/>
    <entity index="53" value="0"/>
    <entity index="54" value="0"/>
    <entity index="55" value="0"/>
    <entity index="56" value="0"/>
    <entity index="57" value="0"/>
    <entity index="58" value="0"/>
    <entity index="59" value="0"/>
    <entity index="60" value="0"/>
    <entity index="61" value="0"/>
    <entity index="62" value="0"/>
    <entity index="63" value="0"/>
    <entity index="64" value="0"/>
    <entity index="65" value="0"/>
    <entity index="66" value="0"/>
    <entity index="67" value="0"/>
    <entity index="68" value="0"/>
    <entity index="69" value="0"/>
    <entity index="70" value="0"/>
    <entity index="71" value="0"/>
    <entity index="72" value="0"/>
    <entity index="73" value="0"/>
    <entity index="74" value="0"/>
    <entity index="75" value="0"/>
    <entity index="76" value="0"/>
    <entity index="77" value="0"/>
    <entity index="78" value="0"/>
    <entity index="79" value="0"/>
    <entity index="80" value="0"/>
    <entity index="81" value="0"/>
    <entity index="82" value="0"/>
    <entity index="83" value="0"/>
    <entity index="84" value="0"/>
    <entity index="85" value="0"/>
    <entity index="86" value="0"/>
    <entity index="87" value="0"/>
    <entity index="88" value="0"/>
    <entity index="89" value="0"/>
    <entity index="90" value="0"/>
    <entity index="91" value="0"/>
    <entity index="92" value="0"/>
    <entity index="93" value="0"/>
    <entity index="94" value="0"/>
    <entity index="95" value="0"/>
    <entity index="96" value="0"/>
    <entity index="97" value="0"/>
    <entity index="98" value="0"/>
    <entity index="99" value="0"/>
    <entity index="100" value="0"/>
    <entity index="101" value="0"/>
    <entity index="102" value="0"/>
    <entity index="103" value="0"/>
    <entity index="104" value="0"/>
    <entity index="105" value="0"/>
    <entity index="106" value="0"/>
    <entity index="107" value="0"/>
    <entity index="108" value="0"/>
    <entity index="109" value="0"/>
    <entity index="110" value="0"/>
    <entity index="111" value="0"/>
    <entity index="112" value="0"/>
    <entity index="113" value="0"/>
    <entity index="114" value="0"/>
    <entity index="115" value="0"/>
    <entity index="116" value="0"/>
    <entity index="117" value="0"/>
    <entity index="118" value="0"/>
    <entity index="119" value="0"/>
    <entity index="120" value="0"/>
    <entity index="121" value="0"/>
    <entity index="122" value="0"/>
    <entity index="123" value="0"/>
    <entity index="124" value="0"/>
    <entity index="125" value="0"/>
    <entity index="126" value="0"/>
    <entity index="127" value="0"/>
    <entity index="128" value="0"/>
    <entity index="129" value="0"/>
    <entity index="130" value="0"/>
    <entity index="131" value="0"/>
    <entity index="132" value="0"/>
    <entity index="133" value="0"/>
    <entity index="134" value="0"/>
    <entity index="135" value="0"/>
    <entity index="136" value="0"/>
    <entity index="137" value="0"/>
    <entity index="138" value="0"/>
    <entity index="139" value="0"/>
    <entity index="140" value="0"/>
    <entity index="141" value="0"/>
    <entity index="142" value="0"/>
    <entity index="143" value="0"/>
    <entity index="144" value="0"/>
    <entity index="145" value="2"/>
    <entity index="146" value="0"/>
    <entity index="147" value="1"/>
    <entity index="148" value="0"/>
    <entity index="149" value="2"/>
    <entity index="150" value="0"/>
    <entity index="151" value="3"/>
    <entity index="152" value="0"/>
    <entity index="153" value="0"/>
    <entity index="154" value="0"/>
    <entity index="155" value="0"/>
    <entity index="156" value="0"/>
    <entity index="157" value="0"/>
    <entity index="158" value="0"/>
    <entity index="159" value="0"/>
    <entity index="160" value="0"/>
    <entity index="161" value="0"/>
    <entity index="162" value="0"/>
    <entity index="163" value="0"/>
    <entity index="164" value="0"/>
    <entity index="165" value="0"/>
    <entity index="166" value="0"/>
    <entity index="167" value="0"/>
    <entity index="168" value="0"/>
    <entity index="169" value="0"/>
    <entity index="170" value="0"/>
    <entity index="171" value="0"/>
    <entity index="172" value="0"/>
    <entity index="173" value="0"/>
    <entity index="174" value="0"/>
    <entity index="175" value="0"/>
    <entity index="176" value="0"/>
    <entity index="177" value="0"/>
    <entity index="178" value="0"/>
    <entity index="179" value="0"/>
    <entity index="180" value="0"/>
    <entity index="181" value="0"/>
    <entity index="182" value="0"/>
    <entity index="183" value="0"/>
    <entity index="184" value="0"/>
    <entity index="185" value="0"/>
    <entity index="186" value="0"/>
    <entity index="187" value="0"/>
    <entity index="188" value="0"/>
    <entity index="189" value="0"/>
    <entity index="190" value="0"/>
    <entity index="191" value="0"/>
    <entity index="192" value="0"/>
    <entity index="193" value="0"/>
    <entity index="194" value="0"/>
    <entity index="195" value="0"/>
    <entity index="196" value="0"/>
    <entity index="197" value="0"/>
    <entity index="198" value="0"/>
    <entity index="199" value="0"/>
    <entity index="200" value="0"/>
    <entity index="201" value="1"/>
    <entity index="202" value="0"/>
    <entity index="203" value="2"/>
    <entity index="204" value="0"/>
    <entity index="205" value="3"/>
    <entity index="206" value="0"/>
    <entity index="207" value="2"/>
    <entity index="208" value="2"/>
    <entity index="209" value="3"/>
    <entity index="210" value="2"/>
    <entity index="211" value="1"/>
    <entity index="212" value="0"/>
    <entity index="213" value="0"/>
    <entity index="214" value="0"/>
    <entity index="215" value="0"/>
    <entity index="216" value="0"/>
    <entity index="217" value="0"/>
    <entity index="218" value="0"/>
    <entity index="219" value="0"/>
    <entity index="220" value="0"/>
    <entity index="221" value="0"/>
    <entity index="222" value="0"/>
    <entity index="223" value="0"/>
    <entity index="224" value="0"/>
    <entity index="225" value="0"/>
    <entity index="226" value="0"/>
    <entity index="227" value="0"/>
    <entity index="228" value="0"/>
    <entity index="229" value="2"/>
    <entity index="230" value="0"/>
    <entity index="231" value="1"/>
    <entity index="232" value="0"/>
    <entity index="233" value="2"/>
    <entity index="234" value="0"/>
    <entity index="235" value="3"/>
    <entity index="236" value="2"/>
    <entity index="237" value="1"/>
    <entity index="238" value="2"/>
    <entity index="239" value="3"/>
    <entity index="240" value="0"/>
    <entity index="241" value="0"/>
    <entity index="242" value="0"/>
    <entity index="243" value="0"/>
    <entity index="244" value="0"/>
    <entity index="245" value="0"/>
    <entity index="246" value="0"/>
    <entity index="247" value="0"/>
    <entity index="248" value="0"/>
    <entity index="249" value="0"/>
    <entity index="250" value="0"/>
    <entity index="251" value="0"/>
    <entity index="252" value="0"/>
    <entity index="253" value="0"/>
    <entity index="254" value="0"/>
    <entity index="255" value="0"/>
    <entity index="256" value="0"/>
    <entity index="257" value="0"/>
    <entity index="258" value="0"/>
    <entity index="259" value="0"/>
    <entity index="260" value="0"/>
    <entity index="261" value="0"/>
    <entity index="262" value="0"/>
    <entity index="263" value="0"/>
    <entity index="264" value="0"/>
    <entity index="265" value="0"/>
    <entity index="266" value="0"/>
    <entity index="267" value="0"/>
    <entity index="268" value="0"/>
    <entity index="269" value="0"/>
    <entity index="270" value="0"/>
    <entity index="271" value="0"/>
    <entity index="272" value="0"/>
    <entity index="273" value="0"/>
    <entity index="274" value="0"/>
    <entity index="275" value="0"/>
    <entity index="276" value="0"/>
    <entity index="277" value="0"/>
    <entity index="278" value="0"/>
    <entity index="279" value="0"/>
    <entity index="280" value="2"/>
    <entity index="281" value="1"/>
    <entity index="282" value="2"/>
    <entity index="283" value="3"/>
    <entity index="284" value="0"/>
    <entity index="285" value="0"/>
    <entity index="286" value="0"/>
    <entity index="287" value="0"/>
    <entity index="288" value="0"/>
    <entity index="289" value="0"/>
    <entity index="290" value="0"/>
    <entity index="291" value="0"/>
    <entity index="292" value="0"/>
    <entity index="293" value="0"/>
    <entity index="294" value="0"/>
    <entity index="295" value="0"/>
    <entity index="296" value="0"/>
    <entity index="297" value="0"/>
    <entity index="298" value="0"/>
    <entity index="299" value="0"/>
    <entity index="300" value="0"/>
    <entity index="301" value="0"/>
    <entity index="302" value="0"/>
    <entity index="303" value="0"/>
    <entity index="304" value="0"/>
    <entity index="305" value="0"/>
    <entity index="306" value="0"/>
    <entity index="307" value="0"/>
    <entity index="308" value="0"/>
    <entity index="309" value="0"/>
    <entity index="310" value="0"/>
    <entity index="311" value="0"/>
    <entity index="312" value="0"/>
    <entity index="313" value="0"/>
    <entity index="314" value="0"/>
    <entity index="315" value="0"/>
    <entity index="316" value="0"/>
    <entity index="317" value="0"/>
    <entity index="318" value="0"/>
    <entity index="319" value="0"/>
    <entity index="320" value="0"/>
    <entity index="321" value="0"/>
    <entity index="322" value="0"/>
    <entity index="323" value="0"/>
    <entity index="324" value="0"/>
    <entity index="325" value="0"/>
    <entity index="326" value="0"/>
    <entity index="327" value="0"/>
    <entity index="328" value="0"/>
    <entity index="329" value="0"/>
    <entity index="330" value="0"/>
    <entity index="331" value="0"/>
    <entity index="332" value="2"/>
    <entity index="333" value="1"/>
    <entity index="334" value="2"/>
    <entity index="335" value="3"/>
    <entity index="336" value="0"/>
    <entity index="337" value="0"/>
    <entity index="338" value="0"/>
    <entity index="339" value="0"/>
    <entity index="340" value="0"/>
    <entity index="341" value="2"/>
    <entity index="342" value="0"/>
    <entity index="343" value="1"/>
    <entity index="344" value="0"/>
    <entity index="345" value="2"/>
    <entity index="346" value="0"/>
    <entity index="347" value="3"/>
    <entity index="348" value="0"/>
    <entity index="349" value="0"/>
    <entity index="350" value="0"/>
    <entity index="351" value="0"/>
    <entity index="352" value="0"/>
    <entity index="353" value="0"/>
    <entity index="354" value="0"/>
    <entity index="355" value="0"/>
    <entity index="356" value="0"/>
    <entity index="357" value="0"/>
    <entity index="358" value="0"/>
    <entity index="359" value="0"/>
    <entity index="360" value="0"/>
    <entity index="361" value="0"/>
    <entity index="362" value="0"/>
    <entity index="363" value="0"/>
  </mesh_function>
</dolfin>